qbusyindicator/__init__.py
qbusyindicator/busyindicator.py
qbusyindicator/examples/__init__.py
qbusyindicator/examples/demo.py
qbusyindicator/examples/loading.gif
pyqt6_overlay_busy_indicator-1.6.dist-info/LICENSE.txt
pyqt6_overlay_busy_indicator-1.6.dist-info/METADATA
pyqt6_overlay_busy_indicator-1.6.dist-info/WHEEL
pyqt6_overlay_busy_indicator-1.6.dist-info/top_level.txt
pyqt6_overlay_busy_indicator-1.6.dist-info/RECORD
